pythics/__init__.py
pythics/object.py
pythics/vector.py
pythics-0.0.1.dist-info/LICENSE
pythics-0.0.1.dist-info/METADATA
pythics-0.0.1.dist-info/WHEEL
pythics-0.0.1.dist-info/top_level.txt
pythics-0.0.1.dist-info/RECORD
