Metadata-Version: 2.1
Name: pythics
Version: 0.0.1
Summary: Basic 2D physics library
Home-page: https://github.com/DarkKnight8034/pythics
Author: Kody Schram
Author-email: kody.schram@icloud.com
Requires-Python: >=3.7
License-File: LICENSE
